genexpa/__init__.py
genexpa/main.py
genexpa/core/__init__.py
genexpa/core/actions.py
genexpa/core/explib.py
genexpa/core/helpers.py
genexpa/core/normfinder.py
genexpa/core/system.py
genexpa/uis/LineModelDialog.py
genexpa/uis/MainWindowApp.py
genexpa/uis/ReadFromCombinedDialog.py
genexpa/uis/TableDisplayDialog.py
genexpa/uis/WaitPopup.py
genexpa/uis/__init__.py
genexpa/uis/uis/LineModelDialogUI.py
genexpa/uis/uis/MainWindowUI.py
genexpa/uis/uis/ReadFromCombinedDialogUI.py
genexpa/uis/uis/TableDisplayDialogUI.py
genexpa/uis/uis/WaitPopupUI.py
genexpa/uis/uis/__init__.py
GenExpA-0.0.5.dist-info/LICENSE
GenExpA-0.0.5.dist-info/METADATA
GenExpA-0.0.5.dist-info/WHEEL
GenExpA-0.0.5.dist-info/entry_points.txt
GenExpA-0.0.5.dist-info/top_level.txt
GenExpA-0.0.5.dist-info/RECORD
