Metadata-Version: 2.1
Name: GenExpA
Version: 0.0.5
Summary: Comprehensive tool based on the new workflow for qPCR data analysis
Home-page: UNKNOWN
Author: Dawid Maciazek
License: UNKNOWN
Platform: UNKNOWN
Requires-Python: >=3.6
Requires-Dist: PySide2 (>=5.15.2)
Requires-Dist: numpy (>=1.19.5)
Requires-Dist: cycler (>=0.10.0)
Requires-Dist: et-xmlfile (>=1.1.0)
Requires-Dist: kiwisolver (>=1.3.1)
Requires-Dist: matplotlib (>=3.3.4)
Requires-Dist: openpyxl (>=3.0.7)
Requires-Dist: pandas (>=1.1.5)
Requires-Dist: patsy (>=0.5.1)
Requires-Dist: Pillow (>=8.2.0)
Requires-Dist: pyparsing (>=2.4.7)
Requires-Dist: python-dateutil (>=2.8.1)
Requires-Dist: pytz (>=2021.1)
Requires-Dist: scipy (>=1.5.4)
Requires-Dist: scikit-posthocs (>=0.6.7)
Requires-Dist: seaborn (>=0.11.1)
Requires-Dist: shiboken2 (>=5.15.2)
Requires-Dist: six (>=1.16.0)
Requires-Dist: statsmodels (>=0.12.2)
Requires-Dist: xlrd (>=1.2.0)
